README.md
setup.py
py_switchcase.egg-info/PKG-INFO
py_switchcase.egg-info/SOURCES.txt
py_switchcase.egg-info/dependency_links.txt
py_switchcase.egg-info/top_level.txt
switchcase/__init__.py
switchcase/switchcase.py