Metadata-Version: 1.2
Name: py-switchcase
Version: 0.1.0
Summary: Switches in Python
Home-page: https://github.com/3jackdaws/py-switchcase
Author: Ian Murphy
Author-email: 3jackdaws@gmail.com
License: MIT
Platform: UNKNOWN
Requires-Python: >=3
